{
  "Model 3 Long Range AWD": {
    "acceleration": "4.4 secs",
    "batteryPack": "75 kWh",
    "curbWeight": "1847 kg",
    "dimensions": "4694 x 1850 x 1443",
    "efficiency": "16 kWh / 100 km",
    "enginePower": "346 hp",
    "engineTorque": "527 Nm",
    "range": "465 km",
    "topSpeed": "225 km/h",
    "wheelBase": "2875 mm"
  },
  "Model 3 Long Range RWD": {
    "acceleration": "5.2 secs",
    "batteryPack": "75 kWh",
    "curbWeight": "1726 kg",
    "dimensions": "4694 x 1850 x 1443",
    "efficiency": "14 kWh / 100 km",
    "enginePower": "258 hp",
    "engineTorque": "430 Nm",
    "range": "501 km",
    "topSpeed": "225 km/h",
    "wheelBase": "2875 mm"
  },
  "Model 3 Mid Range": {
    "acceleration": "5.1 secs",
    "batteryPack": "62 kWh",
    "curbWeight": "1672 kg",
    "dimensions": "4694 x 1850 x 1443",
    "efficiency": "15 kWh / 100 km",
    "enginePower": "258 hp",
    "engineTorque": "416 Nm",
    "range": "395 km",
    "topSpeed": "225 km/h",
    "wheelBase": "2875 mm"
  },
  "Model 3 Performance": {
    "acceleration": "3.3 secs",
    "batteryPack": "75 kWh",
    "curbWeight": "1847 kg",
    "dimensions": "4694 x 1850 x 1443",
    "efficiency": "13 kWh / 100 km",
    "enginePower": "450 hp",
    "engineTorque": "639 Nm",
    "range": "451 km",
    "topSpeed": "260 km/h",
    "wheelBase": "2875 mm"
  },
  "Model 3 Standard Range": {
    "acceleration": "5.8 secs",
    "batteryPack": "50 kWh",
    "curbWeight": "1611 kg",
    "dimensions": "4694 x 1850 x 1443",
    "efficiency": "13 kWh / 100 km",
    "enginePower": "201 hp",
    "engineTorque": "350 Nm",
    "range": "325 km",
    "topSpeed": "210 km/h",
    "wheelBase": "2875 mm"
  },
  "Model 3 Standard Range Plus": {
    "acceleration": " 5.6 secs",
    "batteryPack": "50 kWh",
    "curbWeight": "1704 kg",
    "dimensions": "4694 x 1850 x 1443",
    "efficiency": "14 kWh / 100 km",
    "enginePower": "201 hp",
    "engineTorque": "350 Nm",
    "range": "358 km",
    "topSpeed": "225 km/h",
    "wheelBase": "2875 mm"
  },
  "Model S 100D": {
    "acceleration": "4.3 secs",
    "batteryPack": "100 kWh",
    "curbWeight": "2215 kg",
    "dimensions": "4971 x 1963 x 1445",
    "efficiency": "16 kWh / 100 km",
    "enginePower": "517 hp",
    "engineTorque": "660 Nm",
    "range": "477 km",
    "topSpeed": "250 km/h",
    "wheelBase": "2959 mm"
  },
  "Model S 60": {
    "acceleration": "5.8 secs",
    "batteryPack": "60 kWh",
    "curbWeight": "1961 kg",
    "dimensions": "4971 x 1963 x 1445",
    "efficiency": "16 kWh / 100 km",
    "enginePower": "302 hp",
    "engineTorque": "430 Nm",
    "range": "328 km",
    "topSpeed": "210 km/h",
    "wheelBase": "2959 mm"
  },
  "Model S 60D": {
    "acceleration": "5.4 secs",
    "batteryPack": "60 kWh",
    "curbWeight": "2090 kg",
    "dimensions": "4971 x 1963 x 1445",
    "efficiency": "15.4 kWh / 100 km",
    "enginePower": "329 hp",
    "engineTorque": "525 Nm",
    "range": "346 km",
    "topSpeed": "210 km/h",
    "wheelBase": "2959 mm"
  },
  "Model S 70": {
    "acceleration": "5.8 secs",
    "batteryPack": "70 kWh",
    "curbWeight": "2000 kg",
    "dimensions": "4971 x 1963 x 1445",
    "efficiency": "16.7 kWh / 100 km",
    "enginePower": "315 hp",
    "engineTorque": "441 Nm",
    "range": "332 km",
    "topSpeed": "230 km/h",
    "wheelBase": "2959 mm"
  },
  "Model S 70D": {
    "acceleration": "5.4 secs",
    "batteryPack": "70 kWh",
    "curbWeight": "2090 kg",
    "dimensions": "4971 x 1963 x 1445",
    "efficiency": "15.8 kWh / 100 km",
    "enginePower": "329 hp",
    "engineTorque": "525 Nm",
    "range": "368 km",
    "topSpeed": "230 km/h",
    "wheelBase": "2959 mm"
  },
  "Model S 75": {
    "acceleration": "4.5 secs",
    "batteryPack": "75 kWh",
    "curbWeight": "2000 kg",
    "dimensions": "4978 x 1963 x 1445",
    "efficiency": "15.6 kWh / 100 km",
    "enginePower": "315 hp",
    "engineTorque": "441 Nm",
    "range": "386 km",
    "topSpeed": "230 km/h",
    "wheelBase": "2959 mm"
  },
  "Model S 75D": {
    "acceleration": "4.4 secs",
    "batteryPack": "75 kWh",
    "curbWeight": "2090 kg",
    "dimensions": "4978 x 1963 x 1445",
    "efficiency": "15.3 kWh / 100 km",
    "enginePower": "329 hp",
    "engineTorque": "658 Nm",
    "range": "404 km",
    "topSpeed": "230 km/h",
    "wheelBase": "2959 mm"
  },
  "Model S 85": {
    "acceleration": "5.6 secs",
    "batteryPack": "85 kWh",
    "curbWeight": "2108 kg",
    "dimensions": "4971 x 1963 x 1445",
    "efficiency": "16.9 kWh / 100 km",
    "enginePower": "373 hp",
    "engineTorque": "441 Nm",
    "range": "365 km",
    "topSpeed": "230 km/h",
    "wheelBase": "2959 mm"
  },
  "Model S 85D": {
    "acceleration": "5.2 secs",
    "batteryPack": "85 kWh",
    "curbWeight": "2188 kg",
    "dimensions": "4971 x 1963 x 1445",
    "efficiency": "16.1 kWh / 100 km",
    "enginePower": "417 hp",
    "engineTorque": "658 Nm",
    "range": "426 km",
    "topSpeed": "250 km/h",
    "wheelBase": "2959 mm"
  },
  "Model S 90": {
    "acceleration": "3.8 secs",
    "batteryPack": "90 kWh",
    "curbWeight": "2100 kg",
    "dimensions": "4971 x 1963 x 1445",
    "efficiency": "23 kWh / 100 km",
    "enginePower": "382 hp",
    "engineTorque": "440 Nm",
    "range": "435 km",
    "topSpeed": "250 km/h",
    "wheelBase": "2959 mm"
  },
  "Model S 90D": {
    "acceleration": "4 secs",
    "batteryPack": "90 kWh",
    "curbWeight": "2200 kg",
    "dimensions": "4971 x 1963 x 1445",
    "efficiency": "17 kWh / 100 km",
    "enginePower": "417 hp",
    "engineTorque": "658 Nm",
    "range": "456 km",
    "topSpeed": "250 km/h",
    "wheelBase": "2959 mm"
  },
  "Model S Long Range": {
    "acceleration": "3.8 secs",
    "batteryPack": "100 kWh",
    "curbWeight": "2215 kg",
    "dimensions": "4971 x 1963 x 1445",
    "efficiency": "16.4 kWh / 100 km",
    "enginePower": "517 hp",
    "engineTorque": "660 Nm",
    "range": "502 km",
    "topSpeed": "250 km/h",
    "wheelBase": "2959 mm"
  },
  "Model S Long Range Plus": {
    "acceleration": "3.8 secs",
    "batteryPack": "100 kWh",
    "curbWeight": "2215 kg",
    "dimensions": "4971 x 1963 x 1445",
    "efficiency": "16.4 kWh / 100 km",
    "enginePower": "517 hp",
    "engineTorque": "660 Nm",
    "range": "564 km",
    "topSpeed": "250 km/h",
    "wheelBase": "2959 mm"
  },
  "Model S P100D": {
    "acceleration": "2.4 secs",
    "batteryPack": "100 kWh",
    "curbWeight": "2241 kg",
    "dimensions": "4971 x 1963 x 1445",
    "efficiency": "16.3 kWh / 100 km",
    "enginePower": "605 hp",
    "engineTorque": "967 Nm",
    "range": "488 km",
    "topSpeed": "250 km/h",
    "wheelBase": "2959 mm"
  },
  "Model S P85": {
    "acceleration": "4.4 secs",
    "batteryPack": "85 kWh",
    "curbWeight": "2112 kg",
    "dimensions": "4971 x 1963 x 1445",
    "efficiency": "16.9 kWh / 100 km",
    "enginePower": "470 hp",
    "engineTorque": "601 Nm",
    "range": "393 km",
    "topSpeed": "210 km/h",
    "wheelBase": "2959 mm"
  },
  "Model S P85+": {
    "acceleration": "4.4 secs",
    "batteryPack": "85 kWh",
    "curbWeight": "2146 kg",
    "dimensions": "4971 x 1963 x 1445",
    "efficiency": "16.9 kWh / 100 km",
    "enginePower": "470 hp",
    "engineTorque": "601 Nm",
    "range": "393 km",
    "topSpeed": "210 km/h",
    "wheelBase": "2959 mm"
  },
  "Model S P85D": {
    "acceleration": "3.3 secs",
    "batteryPack": "85 kWh",
    "curbWeight": "2239 kg",
    "dimensions": "4971 x 1963 x 1445",
    "efficiency": "17.7 kWh / 100 km",
    "enginePower": "463 hp",
    "engineTorque": "931 Nm",
    "range": "390 km",
    "topSpeed": "250 km/h",
    "wheelBase": "2959 mm"
  },
  "Model S P90D": {
    "acceleration": "3 secs",
    "batteryPack": "90 kWh",
    "curbWeight": "2250 kg",
    "dimensions": "4971 x 1963 x 1445",
    "efficiency": "17.7 kWh / 100 km",
    "enginePower": "532 hp",
    "engineTorque": "931 Nm",
    "range": "456 km",
    "topSpeed": "250 km/h",
    "wheelBase": "2959 mm"
  },
  "Model S Performance": {
    "acceleration": "2.6 secs",
    "batteryPack": "100 kWh",
    "curbWeight": "2241 kg",
    "dimensions": "4971 x 1963 x 1445",
    "efficiency": "16.9 kWh / 100 km",
    "enginePower": "785 hp",
    "engineTorque": "967 Nm",
    "range": "480 km",
    "topSpeed": "250 km/h",
    "wheelBase": "2959 mm"
  },
  "Model S Plaid": {
    "acceleration": "2.1 secs",
    "batteryPack": "95 kWh",
    "curbWeight": "2241 kg",
    "dimensions": "4971 x 1963 x 1445",
    "efficiency": "16.9 kWh / 100 km",
    "enginePower": "1100 hp",
    "engineTorque": "??? Nm",
    "range": "560 km",
    "topSpeed": "250 km/h",
    "wheelBase": "2959 mm"
  },
  "Model S Standard Range": {
    "acceleration": "4.2 secs",
    "batteryPack": "80 kWh",
    "curbWeight": "2090 kg",
    "dimensions": "4971 x 1963 x 1445",
    "efficiency": "17.8 kWh / 100 km",
    "enginePower": "329 hp",
    "engineTorque": "658 Nm",
    "range": "414 km",
    "topSpeed": "250 km/h",
    "wheelBase": "2959 mm"
  },
  "Model X 100D": {
    "acceleration": "4.9 secs",
    "batteryPack": "100 kWh",
    "curbWeight": "2459 kg",
    "dimensions": "5037 x 2070 x 1626",
    "efficiency": "18 kWh / 100 km",
    "enginePower": "517 hp",
    "engineTorque": "660 Nm",
    "range": "398 km",
    "topSpeed": "250 km/h",
    "wheelBase": "2964 mm"
  },
  "Model X 75D": {
    "acceleration": "5.2 secs",
    "batteryPack": "75 kWh",
    "curbWeight": "2330 kg",
    "dimensions": "5037 x 2070 x 1626",
    "efficiency": "18 kWh / 100 km",
    "enginePower": "329 hp",
    "engineTorque": "658 Nm",
    "range": "316 km",
    "topSpeed": "210 km/h",
    "wheelBase": "2964 mm"
  },
  "Model X 90D": {
    "acceleration": "5 secs",
    "batteryPack": "90 kWh",
    "curbWeight": "2390 kg",
    "dimensions": "5037 x 2070 x 1626",
    "efficiency": "18 kWh / 100 km",
    "enginePower": "417 hp",
    "engineTorque": "658 Nm",
    "range": "403 km",
    "topSpeed": "250 km/h",
    "wheelBase": "2964 mm"
  },
  "Model X Long Range": {
    "acceleration": "4.6 secs",
    "batteryPack": "100 kWh",
    "curbWeight": "2459 kg",
    "dimensions": "5037 x 2070 x 1626",
    "efficiency": "19.7 kWh / 100 km",
    "enginePower": "417 hp",
    "engineTorque": "660 Nm",
    "range": "479 km",
    "topSpeed": "250 km/h",
    "wheelBase": "2964 mm"
  },
  "Model X Long Range Plus": {
    "acceleration": "4.6 secs",
    "batteryPack": "100 kWh",
    "curbWeight": "2459 kg",
    "dimensions": "5037 x 2070 x 1626",
    "efficiency": "19.7 kWh / 100 km",
    "enginePower": "417 hp",
    "engineTorque": "660 Nm",
    "range": "529 km",
    "topSpeed": "250 km/h",
    "wheelBase": "2964 mm"
  },
  "Model X P100D": {
    "acceleration": "3 secs",
    "batteryPack": "100 kWh",
    "curbWeight": "2509 kg",
    "dimensions": "5037 x 2070 x 1626",
    "efficiency": "18.7 kWh / 100 km",
    "enginePower": "605 hp",
    "engineTorque": "967 Nm",
    "range": "393 km",
    "topSpeed": "250 km/h",
    "wheelBase": "2964 mm"
  },
  "Model X P90D": {
    "acceleration": "3.4 secs",
    "batteryPack": "90 kWh",
    "curbWeight": "2440 kg",
    "dimensions": "5037 x 2070 x 1626",
    "efficiency": "16.5 kWh / 100 km",
    "enginePower": "532 hp",
    "engineTorque": "931 Nm",
    "range": "330 km",
    "topSpeed": "250 km/h",
    "wheelBase": "2964 mm"
  },
  "Model X Performance": {
    "acceleration": "2.9 secs",
    "batteryPack": "100 kWh",
    "curbWeight": "2509 kg",
    "dimensions": "5037 x 2070 x 1626",
    "efficiency": "16.5 kWh / 100 km",
    "enginePower": "785 hp",
    "engineTorque": "967 Nm",
    "range": "402 km",
    "topSpeed": "250 km/h",
    "wheelBase": "2964 mm"
  },
  "Model X Plaid": {
    "acceleration": "2.6 secs",
    "batteryPack": "100 kWh",
    "curbWeight": "2459 kg",
    "dimensions": "5037 x 2070 x 1626",
    "efficiency": "16.5 kWh / 100 km",
    "enginePower": "?? hp",
    "engineTorque": "660 Nm",
    "range": "547 km",
    "topSpeed": "250 km/h",
    "wheelBase": "2964 mm"
  },
  "Model X Standard Range": {
    "acceleration": "4.8 secs",
    "batteryPack": "80 kWh",
    "curbWeight": "2407 kg",
    "dimensions": "5037 x 2070 x 1626",
    "efficiency": "21.3 kWh / 100 km",
    "enginePower": "329 hp",
    "engineTorque": "658 Nm",
    "range": "520 km",
    "topSpeed": "250 km/h",
    "wheelBase": "2964 mm"
  },
  "Model Y Long Range AWD": {
    "acceleration": "5.1 secs",
    "batteryPack": "75 kWh",
    "curbWeight": "2003 kg",
    "dimensions": "4750 x 1920 x 1624",
    "efficiency": "16.7 kWh / 100 km",
    "enginePower": "384 hp",
    "engineTorque": "510 Nm",
    "range": "524 km",
    "topSpeed": "250 km/h",
    "wheelBase": "2890 mm"
  },
  "Model Y Long Range RWD": {
    "acceleration": "5.9 secs",
    "batteryPack": "75 kWh",
    "curbWeight": "2003 kg",
    "dimensions": "4750 x 1920 x 1624",
    "efficiency": "14 kWh / 100 km",
    "enginePower": "258 hp",
    "engineTorque": "430 Nm",
    "range": "540 km",
    "topSpeed": "250 km/h",
    "wheelBase": "2890 mm"
  },
  "Model Y Performance": {
    "acceleration": "3.5 secs",
    "batteryPack": "75 kWh",
    "curbWeight": "2003 kg",
    "dimensions": "4750 x 1920 x 1624",
    "efficiency": "17.4 kWh / 100 km",
    "enginePower": "456 hp",
    "engineTorque": "673 Nm",
    "range": "507 km",
    "topSpeed": "250 km/h",
    "wheelBase": "2890 mm"
  },
  "Model Y Standard Range": {
    "acceleration": "6.3 secs",
    "batteryPack": "50 kWh",
    "curbWeight": "2003 kg",
    "dimensions": "4750 x 1920 x 1624",
    "efficiency": "13 kWh / 100 km",
    "enginePower": "201 hp",
    "engineTorque": "350 Nm",
    "range": "390 km",
    "topSpeed": "193 km/h",
    "wheelBase": "2890 mm"
  }
}
